skyvern_llamaindex/__init__.py
skyvern_llamaindex/agent.py
skyvern_llamaindex/client.py
skyvern_llamaindex/py.typed
skyvern_llamaindex/settings.py
skyvern_llamaindex-0.2.2.dist-info/METADATA
skyvern_llamaindex-0.2.2.dist-info/WHEEL
skyvern_llamaindex-0.2.2.dist-info/RECORD
