Metadata-Version: 2.4
Name: skyvern-llamaindex
Version: 0.2.2
Summary: Skyvern integration for LlamaIndex
Author-email: lawyzheng <lawy@skyvern.com>
Requires-Python: <3.14,>=3.11
Requires-Dist: llama-index<0.13,>=0.12.19
Requires-Dist: skyvern>=0.2.0
Requires-Dist: urllib3>=2.6.0
